{
	"ambient_light": {
		"intensity": 0.6
	},
	"aspect_ratio": "16:9",
	"blender_camera": {
		"clip_end": 450.0,
		"clip_start": 0.1,
		"lens": 60.0,
		"lens_unit": "FOV",
		"location": [
			12.9950953750417,
			14.6503472017566,
			1.5
		],
		"rotation_euler": [
			-1.18128511508083,
			0.0,
			-2.28071977716174
		],
		"rotation_mode": "XYZ",
		"sensor_fit": "AUTO",
		"sensor_height": 18.0,
		"sensor_width": 32.0,
		"shift_x": 0.0,
		"shift_y": 0.0,
		"type": "PERSP"
	},
	"blender_script": "\nimport bpy\nimport bmesh\nfrom mathutils import Vector, Euler\n\n# Clear existing camera and target\nif \"Camera\" in bpy.data.objects:\n    bpy.data.objects.remove(bpy.data.objects[\"Camera\"], do_unlink=True)\nif \"CameraTarget\" in bpy.data.objects:\n    bpy.data.objects.remove(bpy.data.objects[\"CameraTarget\"], do_unlink=True)\n\n# Create camera\nbpy.ops.object.camera_add()\ncamera = bpy.context.object\ncamera.name = \"Camera\"\n\n# Set camera properties\ncamera.location = (12.995095375041736, 14.650347201756633, 1.5)\ncamera.rotation_euler = (-1.1812851150808255, 0, -2.280719777161741)\ncamera.rotation_mode = 'XYZ'\ncamera.data.type = 'PERSP'\ncamera.data.lens_unit = 'FOV'\ncamera.data.lens = 60\ncamera.data.clip_start = 0.1\ncamera.data.clip_end = 450\ncamera.data.sensor_width = 32\ncamera.data.sensor_height = 18\ncamera.data.sensor_fit = 'AUTO'\ncamera.data.shift_x = 0\ncamera.data.shift_y = 0\n\n# Create camera target (Empty object)\nbpy.ops.object.empty_add(type='PLAIN_AXES')\ntarget = bpy.context.object\ntarget.name = \"CameraTarget\"\ntarget.location = (10.115130689223983, 23.901295011824807, -0.9750288935358915)\ntarget.rotation_euler = (0, 0, 0)\ntarget.empty_display_size = 1\n\n# Set camera to track target\ncamera.constraints.new(type='TRACK_TO')\ncamera.constraints[\"Track To\"].target = target\ncamera.constraints[\"Track To\"].track_axis = 'TRACK_NEGATIVE_Z'\ncamera.constraints[\"Track To\"].up_axis = 'UP_Y'\n\n# Set camera as active camera\nbpy.context.scene.camera = camera\n\nprint(\"Camera setup complete!\")\nprint(f\"Camera location: {camera.location}\")\nprint(f\"Camera rotation: {camera.rotation_euler}\")\nprint(f\"Target location: {target.location}\")\nprint(f\"Camera FOV: {camera.data.lens}\")\n",
	"blender_target": {
		"empty_display_size": 1.0,
		"empty_display_type": "PLAIN_AXES",
		"location": [
			10.115130689224,
			23.9012950118248,
			-0.975028893535892
		],
		"rotation_euler": [
			0.0,
			0.0,
			0.0
		],
		"rotation_mode": "XYZ",
		"type": "EMPTY"
	},
	"coordinate_system": "right_handed_y_up",
	"day_render": true,
	"directional_light": {
		"cast_shadow": false,
		"color": {
			"b": 0.871367119195957,
			"g": 0.938685728456504,
			"r": 1.0
		},
		"intensity": 0.8,
		"position": {
			"x": 25.0,
			"y": 35.0,
			"z": -10.0
		},
		"target": {
			"x": 0.0,
			"y": 0.0,
			"z": 0.0
		}
	},
	"floor_plan_data": {
		"direction": "n",
		"directionangle": 0.0,
		"grids": {

		},
		"groups": {

		},
		"guides": {
			"circular": {

			},
			"horizontal": {

			},
			"vertical": {

			}
		},
		"height": 1363.10769865368,
		"layers": {
			"layer-2": {
				"altitude": 0.0,
				"areas": {
					"a-1773049007953-zohbv6kd": {
						"ceiling_properties": {
							"height": 300.0,
							"isvisible": true,
							"material": {
								"aoUrl": null,
								"color": "#fafaf7",
								"displacementUrl": null,
								"emissionUrl": null,
								"flipY": false,
								"mapUrl": null,
								"metalnessUrl": null,
								"normalUrl": null,
								"repeat": [
									1.0,
									1.0
								],
								"rotation": 0.0,
								"roughnessUrl": null,
								"textureId": null
							},
							"thickness": 2.0
						},
						"floor_properties": {
							"height": 0.0,
							"isvisible": true,
							"material": {
								"aoUrl": null,
								"color": "#7a5c45",
								"displacementUrl": null,
								"emissionUrl": null,
								"flipY": false,
								"mapUrl": null,
								"metalnessUrl": null,
								"normalUrl": null,
								"repeat": [
									1.0,
									1.0
								],
								"rotation": 0.0,
								"roughnessUrl": null,
								"textureId": null
							},
							"thickness": 5.0
						},
						"holes": [],
						"id": "a-1773049007953-zohbv6kd",
						"misc": {

						},
						"name": "Room",
						"properties": {
							"height": {
								"length": 0.0
							},
							"texture": "none"
						},
						"prototype": "areas",
						"selected": false,
						"type": "area",
						"vertices": [
							"v-1773049001517-0",
							"v-1773049001517-1",
							"v-1773049004182-1",
							"v-1773049006252-1"
						],
						"visible": true
					}
				},
				"externalAreas": {

				},
				"holes": {
					"h-1773049067364-3fht2rwo": {
						"asset_urls": {
							"GLB_File_URL": "C:\\Zlendo2026\\4k_Unreal_Engine_v1 - godot\\asset_downloads\\cead3da7_Custom_Window_HP.glb",
							"MTL_File_URL": null,
							"OBJ_File_URL": null,
							"SVG_URL": "https://zrealtystoragedev.blob.core.windows.net/asset-library/Windows/Modern_Window1/Svg_window.svg",
							"assetId_3D": 76.0
						},
						"flipX": false,
						"flipZ": false,
						"id": "h-1773049067364-3fht2rwo",
						"line": "l-1773049007948-zjwivojd",
						"materials": {

						},
						"misc": {

						},
						"name": "Bedroom Window",
						"offset": 0.719511796282384,
						"properties": {
							"altitude": {
								"length": 20.0
							},
							"height": {
								"length": 180.0
							},
							"thickness": {
								"length": 16.8
							},
							"width": {
								"length": 112.0
							}
						},
						"prototype": "holes",
						"selected": false,
						"type": "Furniture",
						"visible": true
					}
				},
				"id": "layer-2",
				"items": {
					"09b3efbf-62f7-45f8-96bc-be3b3b11f4ae": {
						"asset_urls": {
							"GLB_File_URL": "C:\\Zlendo2026\\4k_Unreal_Engine_v1 - godot\\asset_downloads\\72771901_Kids_Chair_HP_high.glb",
							"MTL_File_URL": "",
							"OBJ_File_URL": "",
							"SVG_URL": "asset-library/Chair/Kids_Chair/Chair_photorealistic.svg",
							"assetId_3D": 417.0
						},
						"id": "09b3efbf-62f7-45f8-96bc-be3b3b11f4ae",
						"materials": {

						},
						"misc": {

						},
						"mounting_type": "general",
						"name": "Kids Chair",
						"properties": {
							"altitude": {
								"length": 1.0
							},
							"depth": {
								"length": 45.0
							},
							"height": {
								"length": 85.0
							},
							"width": {
								"length": 45.0
							}
						},
						"prototype": "items",
						"rotation": 90.0,
						"selected": false,
						"type": "Kids Chair",
						"visible": true,
						"x": 1022.664,
						"y": -1731.72026739985
					},
					"0de6453e-01b4-44da-a962-cee8f0d48b2a": {
						"asset_urls": {
							"GLB_File_URL": "C:\\Zlendo2026\\4k_Unreal_Engine_v1 - godot\\asset_downloads\\5b5d3737_Kids_Table_HP_high.glb",
							"MTL_File_URL": "",
							"OBJ_File_URL": "",
							"SVG_URL": "asset-library/Table/Kids_Study_Table/Table_photorealistic.svg",
							"assetId_3D": 416.0
						},
						"id": "0de6453e-01b4-44da-a962-cee8f0d48b2a",
						"materials": {

						},
						"misc": {

						},
						"mounting_type": "general",
						"name": "Kids Study Table",
						"properties": {
							"altitude": {
								"length": 1.0
							},
							"depth": {
								"length": 60.0
							},
							"height": {
								"length": 75.0
							},
							"width": {
								"length": 120.0
							}
						},
						"prototype": "items",
						"rotation": -90.0,
						"selected": false,
						"type": "Kids Study Table",
						"visible": true,
						"x": 950.164,
						"y": -1731.72026739985
					},
					"1c3fadc3-06aa-4473-a57a-286440d784fd": {
						"asset_urls": {
							"GLB_File_URL": "C:\\Zlendo2026\\4k_Unreal_Engine_v1 - godot\\asset_downloads\\c8b765ec_Standinglamp_HP_high.glb",
							"MTL_File_URL": "",
							"OBJ_File_URL": "",
							"SVG_URL": "asset-library/Lamp/Minimal_Globe_Floor_Lamp/Standinglamp_photorealistic.svg",
							"assetId_3D": 456.0
						},
						"id": "1c3fadc3-06aa-4473-a57a-286440d784fd",
						"materials": {

						},
						"misc": {

						},
						"mounting_type": "general",
						"name": "Minimal Globe Floor Lamp",
						"properties": {
							"altitude": {
								"length": 1.0
							},
							"depth": {
								"length": 35.0
							},
							"height": {
								"length": 160.0
							},
							"width": {
								"length": 35.0
							}
						},
						"prototype": "items",
						"rotation": 0.0,
						"selected": false,
						"type": "Minimal Globe Floor Lamp",
						"visible": true,
						"x": -155.263,
						"y": -283.384
					},
					"427fcd52-20c2-4b6b-b0b8-bdf67d1e1fd2": {
						"asset_urls": {
							"GLB_File_URL": "C:\\Zlendo2026\\4k_Unreal_Engine_v1 - godot\\asset_downloads\\c8b765ec_Standinglamp_HP_high.glb",
							"MTL_File_URL": "",
							"OBJ_File_URL": "",
							"SVG_URL": "asset-library/Lamp/Minimal_Globe_Floor_Lamp/Standinglamp_photorealistic.svg",
							"assetId_3D": 456.0
						},
						"id": "427fcd52-20c2-4b6b-b0b8-bdf67d1e1fd2",
						"materials": {

						},
						"misc": {

						},
						"mounting_type": "general",
						"name": "Minimal Globe Floor Lamp",
						"properties": {
							"altitude": {
								"length": 1.0
							},
							"depth": {
								"length": 35.0
							},
							"height": {
								"length": 160.0
							},
							"width": {
								"length": 35.0
							}
						},
						"prototype": "items",
						"rotation": 90.0,
						"selected": false,
						"type": "Minimal Globe Floor Lamp",
						"visible": true,
						"x": 1547.732,
						"y": -403.563805571022
					},
					"68a19952-3c96-489d-9a43-2938d79e99dc": {
						"asset_urls": {
							"GLB_File_URL": "C:\\Zlendo2026\\4k_Unreal_Engine_v1 - godot\\asset_downloads\\4d1dced6_Kids_Curtains_HP_high.glb",
							"MTL_File_URL": "",
							"OBJ_File_URL": "",
							"SVG_URL": "asset-library/Curtains/Window_Curtains/Curtains_photorealistic.svg",
							"assetId_3D": 421.0
						},
						"id": "68a19952-3c96-489d-9a43-2938d79e99dc",
						"materials": {

						},
						"misc": {

						},
						"mounting_type": "wall_mount",
						"name": "Window Curtains",
						"properties": {
							"altitude": {
								"length": 5.0
							},
							"depth": {
								"length": 20.0
							},
							"height": {
								"length": 210.0
							},
							"width": {
								"length": 112.0
							}
						},
						"prototype": "items",
						"rotation": -180.0,
						"selected": false,
						"type": "Window Curtains",
						"visible": true,
						"x": 1113.80726834238,
						"y": -1793.16653481987
					},
					"817b67a6-970d-4f95-8d3a-e8c9fd8e7af3": {
						"asset_urls": {
							"GLB_File_URL": "C:\\Zlendo2026\\4k_Unreal_Engine_v1 - godot\\asset_downloads\\154f5158_Kids_Toys_HP_high.glb",
							"MTL_File_URL": "",
							"OBJ_File_URL": "",
							"SVG_URL": "asset-library/Rug/Kids_Toys/Toys_photorealistic.svg",
							"assetId_3D": 426.0
						},
						"id": "817b67a6-970d-4f95-8d3a-e8c9fd8e7af3",
						"materials": {

						},
						"misc": {

						},
						"mounting_type": "general",
						"name": "Kids Toys",
						"properties": {
							"altitude": {
								"length": 2.0
							},
							"depth": {
								"length": 80.0
							},
							"height": {
								"length": 40.0
							},
							"width": {
								"length": 120.0
							}
						},
						"prototype": "items",
						"rotation": 0.0,
						"selected": false,
						"type": "Kids Toys",
						"visible": true,
						"x": 1282.948,
						"y": -1631.167
					},
					"87caa550-1a19-4c89-a7eb-4578746304f9": {
						"asset_urls": {
							"GLB_File_URL": "C:\\Zlendo2026\\4k_Unreal_Engine_v1 - godot\\asset_downloads\\cc863bea_Kids_Bed_HP_high.glb",
							"MTL_File_URL": "",
							"OBJ_File_URL": "",
							"SVG_URL": "asset-library/Beds/Kids_Bed/image (39)_photorealistic.svg",
							"assetId_3D": 423.0
						},
						"id": "87caa550-1a19-4c89-a7eb-4578746304f9",
						"materials": {

						},
						"misc": {

						},
						"mounting_type": "general",
						"name": "Kids Bed",
						"properties": {
							"altitude": {
								"length": 1.0
							},
							"depth": {
								"length": 100.0
							},
							"height": {
								"length": 170.0
							},
							"width": {
								"length": 200.0
							}
						},
						"prototype": "items",
						"rotation": 0.0,
						"selected": false,
						"type": "Kids Bed",
						"visible": true,
						"x": 1282.948,
						"y": -1751.167
					},
					"9b91ed43-9683-4e93-be46-2b4a5572e605": {
						"asset_urls": {
							"GLB_File_URL": "C:\\Zlendo2026\\4k_Unreal_Engine_v1 - godot\\asset_downloads\\5a899cc9_Kids_Shelf_HP_high.glb",
							"MTL_File_URL": "",
							"OBJ_File_URL": "",
							"SVG_URL": "asset-library/Bookshelf/Kids_Single_Rack/WallMountedshelf_photorealistic.svg",
							"assetId_3D": 424.0
						},
						"id": "9b91ed43-9683-4e93-be46-2b4a5572e605",
						"materials": {

						},
						"misc": {

						},
						"mounting_type": "wall_mount",
						"name": "Kids Single Rack",
						"properties": {
							"altitude": {
								"length": 90.0
							},
							"depth": {
								"length": 22.0
							},
							"height": {
								"length": 18.0
							},
							"width": {
								"length": 100.0
							}
						},
						"prototype": "items",
						"rotation": -180.0,
						"selected": false,
						"type": "Kids Single Rack",
						"visible": true,
						"x": 1277.87131163556,
						"y": -1229.503
					},
					"9b95297f-aef9-4b04-801a-3269bdd9c571": {
						"asset_urls": {
							"GLB_File_URL": "C:\\Zlendo2026\\4k_Unreal_Engine_v1 - godot\\asset_downloads\\3fc7f15d_MinimalistCeilingLight_HP.glb",
							"MTL_File_URL": "",
							"OBJ_File_URL": "",
							"SVG_URL": "https://zrealtystoragedev.blob.core.windows.net/asset-library/Ceiling_Lamps/Minimalistic_CeilingLight/Svg_MinimalisticCeilingLight.svg",
							"assetId_3D": 159.0
						},
						"id": "9b95297f-aef9-4b04-801a-3269bdd9c571",
						"materials": {

						},
						"misc": {

						},
						"mounting_type": "ceiling_mount",
						"name": "Minimalistic_CeilingLight",
						"properties": {
							"altitude": {
								"length": 297.9
							},
							"depth": {
								"length": 7.31
							},
							"height": {
								"length": 6.9
							},
							"width": {
								"length": 7.31
							}
						},
						"prototype": "items",
						"rotation": 90.0,
						"selected": false,
						"type": "Minimalistic_CeilingLight",
						"visible": true,
						"x": 1581.73574737445,
						"y": -1282.49925262555
					},
					"9efb0395-95cb-4a46-b784-cc3b2876128e": {
						"asset_urls": {
							"GLB_File_URL": "C:\\Zlendo2026\\4k_Unreal_Engine_v1 - godot\\asset_downloads\\1839107f_Kids_CeilingLamp_HP_high.glb",
							"MTL_File_URL": "",
							"OBJ_File_URL": "",
							"SVG_URL": "asset-library/Ceiling_Lamps/Kids_CeilingLamp/Ceilinglight_photorealistic.svg",
							"assetId_3D": 418.0
						},
						"id": "9efb0395-95cb-4a46-b784-cc3b2876128e",
						"materials": {

						},
						"misc": {

						},
						"mounting_type": "ceiling_mount",
						"name": "Kids CeilingLamp",
						"properties": {
							"altitude": {
								"length": 259.8
							},
							"depth": {
								"length": 60.0
							},
							"height": {
								"length": 45.0
							},
							"width": {
								"length": 60.0
							}
						},
						"prototype": "items",
						"rotation": 270.0,
						"selected": false,
						"type": "Kids CeilingLamp",
						"visible": true,
						"x": 1282.948,
						"y": -1509.835
					},
					"a2857759-d795-445e-9ce0-35cf63342586": {
						"asset_urls": {
							"GLB_File_URL": "C:\\Zlendo2026\\4k_Unreal_Engine_v1 - godot\\asset_downloads\\3fc7f15d_MinimalistCeilingLight_HP.glb",
							"MTL_File_URL": "",
							"OBJ_File_URL": "",
							"SVG_URL": "https://zrealtystoragedev.blob.core.windows.net/asset-library/Ceiling_Lamps/Minimalistic_CeilingLight/Svg_MinimalisticCeilingLight.svg",
							"assetId_3D": 159.0
						},
						"id": "a2857759-d795-445e-9ce0-35cf63342586",
						"materials": {

						},
						"misc": {

						},
						"mounting_type": "ceiling_mount",
						"name": "Minimalistic_CeilingLight",
						"properties": {
							"altitude": {
								"length": 297.9
							},
							"depth": {
								"length": 7.31
							},
							"height": {
								"length": 6.9
							},
							"width": {
								"length": 7.31
							}
						},
						"prototype": "items",
						"rotation": 270.0,
						"selected": false,
						"type": "Minimalistic_CeilingLight",
						"visible": true,
						"x": 1597.2439363084,
						"y": -1752.6789363084
					},
					"baf3686c-eb2c-471c-997e-5c0cfb5548ff": {
						"asset_urls": {
							"GLB_File_URL": "C:\\Zlendo2026\\4k_Unreal_Engine_v1 - godot\\asset_downloads\\3fc7f15d_MinimalistCeilingLight_HP.glb",
							"MTL_File_URL": "",
							"OBJ_File_URL": "",
							"SVG_URL": "https://zrealtystoragedev.blob.core.windows.net/asset-library/Ceiling_Lamps/Minimalistic_CeilingLight/Svg_MinimalisticCeilingLight.svg",
							"assetId_3D": 159.0
						},
						"id": "baf3686c-eb2c-471c-997e-5c0cfb5548ff",
						"materials": {

						},
						"misc": {

						},
						"mounting_type": "ceiling_mount",
						"name": "Minimalistic_CeilingLight",
						"properties": {
							"altitude": {
								"length": 297.9
							},
							"depth": {
								"length": 7.31
							},
							"height": {
								"length": 6.9
							},
							"width": {
								"length": 7.31
							}
						},
						"prototype": "items",
						"rotation": 270.0,
						"selected": false,
						"type": "Minimalistic_CeilingLight",
						"visible": true,
						"x": 989.530030268879,
						"y": -1731.80096973112
					},
					"bc55e0c7-a420-4128-b4ea-5d3843f1b549": {
						"asset_urls": {
							"GLB_File_URL": "C:\\Zlendo2026\\4k_Unreal_Engine_v1 - godot\\asset_downloads\\3fc7f15d_MinimalistCeilingLight_HP.glb",
							"MTL_File_URL": "",
							"OBJ_File_URL": "",
							"SVG_URL": "https://zrealtystoragedev.blob.core.windows.net/asset-library/Ceiling_Lamps/Minimalistic_CeilingLight/Svg_MinimalisticCeilingLight.svg",
							"assetId_3D": 159.0
						},
						"id": "bc55e0c7-a420-4128-b4ea-5d3843f1b549",
						"materials": {

						},
						"misc": {

						},
						"mounting_type": "ceiling_mount",
						"name": "Minimalistic_CeilingLight",
						"properties": {
							"altitude": {
								"length": 297.9
							},
							"depth": {
								"length": 7.31
							},
							"height": {
								"length": 6.9
							},
							"width": {
								"length": 7.31
							}
						},
						"prototype": "items",
						"rotation": 90.0,
						"selected": false,
						"type": "Minimalistic_CeilingLight",
						"visible": true,
						"x": 984.540345182935,
						"y": -1282.87934518294
					},
					"bec6ab5e-e8d3-4fe6-b2ee-cca5154a4aa2": {
						"asset_urls": {
							"GLB_File_URL": "C:\\Zlendo2026\\4k_Unreal_Engine_v1 - godot\\asset_downloads\\ac7fe36e_Modern_AC_HP.glb",
							"MTL_File_URL": "",
							"OBJ_File_URL": "",
							"SVG_URL": "https://zrealtystoragedev.blob.core.windows.net/asset-library/AC/Modern_AC/Modern_AC1.svg",
							"assetId_3D": 44.0
						},
						"id": "bec6ab5e-e8d3-4fe6-b2ee-cca5154a4aa2",
						"materials": {

						},
						"misc": {

						},
						"mounting_type": "wall_mount",
						"name": "Modern_AC",
						"properties": {
							"altitude": {
								"length": 220.0
							},
							"depth": {
								"length": 17.9
							},
							"height": {
								"length": 28.0
							},
							"width": {
								"length": 89.3
							}
						},
						"prototype": "items",
						"rotation": -270.0,
						"selected": false,
						"type": "Modern_AC",
						"visible": true,
						"x": 1636.782,
						"y": -1474.36358933033
					},
					"c9491ca6-0a54-4ef4-8590-080644da7ca0": {
						"asset_urls": {
							"GLB_File_URL": "C:\\Zlendo2026\\4k_Unreal_Engine_v1 - godot\\asset_downloads\\d552c7b6_Kids_Wardrobe_HP_high.glb",
							"MTL_File_URL": "",
							"OBJ_File_URL": "",
							"SVG_URL": "asset-library/Cupboard/Kids_Wardrobe/Wardrobe_photorealistic.svg",
							"assetId_3D": 420.0
						},
						"id": "c9491ca6-0a54-4ef4-8590-080644da7ca0",
						"materials": {

						},
						"misc": {

						},
						"mounting_type": "general",
						"name": "Kids Wardrobe",
						"properties": {
							"altitude": {
								"length": 1.0
							},
							"depth": {
								"length": 55.0
							},
							"height": {
								"length": 180.0
							},
							"width": {
								"length": 90.0
							}
						},
						"prototype": "items",
						"rotation": -270.0,
						"selected": false,
						"type": "Kids Wardrobe",
						"visible": true,
						"x": 1618.232,
						"y": -1756.167
					},
					"cdaa25eb-1aab-428c-9617-c71876839a2b": {
						"asset_urls": {
							"GLB_File_URL": "C:\\Zlendo2026\\4k_Unreal_Engine_v1 - godot\\asset_downloads\\249e09b0_Kids_BookShelf_HP_high.glb",
							"MTL_File_URL": "",
							"OBJ_File_URL": "",
							"SVG_URL": "asset-library/Bookshelf/Kids_Bookshelf/Bookshelf_photorealistic.svg",
							"assetId_3D": 422.0
						},
						"id": "cdaa25eb-1aab-428c-9617-c71876839a2b",
						"materials": {

						},
						"misc": {

						},
						"mounting_type": "wall_mount",
						"name": "Kids Bookshelf",
						"properties": {
							"altitude": {
								"length": 75.0
							},
							"depth": {
								"length": 20.0
							},
							"height": {
								"length": 45.0
							},
							"width": {
								"length": 120.0
							}
						},
						"prototype": "items",
						"rotation": -180.0,
						"selected": false,
						"type": "Kids Bookshelf",
						"visible": true,
						"x": 1487.06486440548,
						"y": -1228.503
					},
					"e955e281-317d-4808-af96-2f5217f3c5f4": {
						"asset_urls": {
							"GLB_File_URL": "C:\\Zlendo2026\\4k_Unreal_Engine_v1 - godot\\asset_downloads\\1a95cc06_Kids_Lamp_HP_high.glb",
							"MTL_File_URL": "",
							"OBJ_File_URL": "",
							"SVG_URL": "asset-library/Lamp/Kids_Table_Lamp/Lamp_photorealistic.svg",
							"assetId_3D": 425.0
						},
						"id": "e955e281-317d-4808-af96-2f5217f3c5f4",
						"materials": {

						},
						"misc": {

						},
						"mounting_type": "general",
						"name": "Kids Table Lamp",
						"properties": {
							"altitude": {
								"length": 76.0
							},
							"depth": {
								"length": 30.0
							},
							"height": {
								"length": 45.0
							},
							"width": {
								"length": 30.0
							}
						},
						"prototype": "items",
						"rotation": 270.0,
						"selected": false,
						"type": "Kids Table Lamp",
						"visible": true,
						"x": 925.164,
						"y": -1734.72026739985
					},
					"fc3e741b-82a4-4dde-9bc9-dbd878b23711": {
						"asset_urls": {
							"GLB_File_URL": "C:\\Zlendo2026\\4k_Unreal_Engine_v1 - godot\\asset_downloads\\562ef3a4_Kids_Rug_HP_high.glb",
							"MTL_File_URL": "",
							"OBJ_File_URL": "",
							"SVG_URL": "asset-library/Rug/Kids_Rug/Rug_photorealistic.svg",
							"assetId_3D": 419.0
						},
						"id": "fc3e741b-82a4-4dde-9bc9-dbd878b23711",
						"materials": {

						},
						"misc": {

						},
						"mounting_type": "floor_mount",
						"name": "Kids Rug",
						"properties": {
							"altitude": {
								"length": 1.0
							},
							"depth": {
								"length": 100.0
							},
							"height": {
								"length": 1.0
							},
							"width": {
								"length": 160.0
							}
						},
						"prototype": "items",
						"rotation": 0.0,
						"selected": false,
						"type": "Kids Rug",
						"visible": true,
						"x": 1282.948,
						"y": -1631.167
					}
				},
				"lines": {
					"l-1773049001516-88vkuras": {
						"holes": [],
						"id": "l-1773049001516-88vkuras",
						"inner_properties": {
							"material": {
								"aoUrl": null,
								"color": "#6ec1b8",
								"displacementUrl": null,
								"emissionUrl": null,
								"flipY": false,
								"mapUrl": null,
								"metalnessUrl": null,
								"normalUrl": null,
								"repeat": [
									1.0,
									1.0
								],
								"rotation": 0.0,
								"roughnessUrl": null,
								"textureId": null
							}
						},
						"misc": {
							"_unitLength": "m"
						},
						"name": "Wall",
						"outer_properties": {
							"material": {
								"aoUrl": null,
								"color": "#7c8eae",
								"displacementUrl": null,
								"emissionUrl": null,
								"flipY": false,
								"mapUrl": null,
								"metalnessUrl": null,
								"normalUrl": null,
								"repeat": [
									1.0,
									1.0
								],
								"rotation": 0.0,
								"roughnessUrl": null,
								"textureId": null
							}
						},
						"properties": {
							"height": {
								"length": 304.8
							},
							"textureA": "Brick",
							"textureB": "Brick",
							"thickness": {
								"length": 22.86
							}
						},
						"prototype": "lines",
						"selected": false,
						"type": "wall",
						"vertices": [
							"v-1773049001517-0",
							"v-1773049001517-1"
						],
						"visible": true
					},
					"l-1773049004182-c3o2nppp": {
						"holes": [],
						"id": "l-1773049004182-c3o2nppp",
						"inner_properties": {
							"material": {
								"aoUrl": null,
								"color": "#6ec1b8",
								"displacementUrl": null,
								"emissionUrl": null,
								"flipY": false,
								"mapUrl": null,
								"metalnessUrl": null,
								"normalUrl": null,
								"repeat": [
									1.0,
									1.0
								],
								"rotation": 0.0,
								"roughnessUrl": null,
								"textureId": null
							}
						},
						"misc": {
							"_unitLength": "m"
						},
						"name": "Wall",
						"outer_properties": {
							"material": {
								"aoUrl": null,
								"color": "#7c8eae",
								"displacementUrl": null,
								"emissionUrl": null,
								"flipY": false,
								"mapUrl": null,
								"metalnessUrl": null,
								"normalUrl": null,
								"repeat": [
									1.0,
									1.0
								],
								"rotation": 0.0,
								"roughnessUrl": null,
								"textureId": null
							}
						},
						"properties": {
							"height": {
								"length": 304.8
							},
							"textureA": "Brick",
							"textureB": "Brick",
							"thickness": {
								"length": 22.86
							}
						},
						"prototype": "lines",
						"selected": false,
						"type": "wall",
						"vertices": [
							"v-1773049001517-1",
							"v-1773049004182-1"
						],
						"visible": true
					},
					"l-1773049006252-pd9mcn52": {
						"holes": [],
						"id": "l-1773049006252-pd9mcn52",
						"inner_properties": {
							"material": {
								"aoUrl": null,
								"color": "#6ec1b8",
								"displacementUrl": null,
								"emissionUrl": null,
								"flipY": false,
								"mapUrl": null,
								"metalnessUrl": null,
								"normalUrl": null,
								"repeat": [
									1.0,
									1.0
								],
								"rotation": 0.0,
								"roughnessUrl": null,
								"textureId": null
							}
						},
						"misc": {
							"_unitLength": "m"
						},
						"name": "Wall",
						"outer_properties": {
							"material": {
								"aoUrl": null,
								"color": "#7c8eae",
								"displacementUrl": null,
								"emissionUrl": null,
								"flipY": false,
								"mapUrl": null,
								"metalnessUrl": null,
								"normalUrl": null,
								"repeat": [
									1.0,
									1.0
								],
								"rotation": 0.0,
								"roughnessUrl": null,
								"textureId": null
							}
						},
						"properties": {
							"height": {
								"length": 304.8
							},
							"textureA": "Brick",
							"textureB": "Brick",
							"thickness": {
								"length": 22.86
							}
						},
						"prototype": "lines",
						"selected": false,
						"type": "wall",
						"vertices": [
							"v-1773049004182-1",
							"v-1773049006252-1"
						],
						"visible": true
					},
					"l-1773049007948-zjwivojd": {
						"holes": [
							"h-1773049067364-3fht2rwo"
						],
						"id": "l-1773049007948-zjwivojd",
						"inner_properties": {
							"material": {
								"aoUrl": null,
								"color": "#6ec1b8",
								"displacementUrl": null,
								"emissionUrl": null,
								"flipY": false,
								"mapUrl": null,
								"metalnessUrl": null,
								"normalUrl": null,
								"repeat": [
									1.0,
									1.0
								],
								"rotation": 0.0,
								"roughnessUrl": null,
								"textureId": null
							}
						},
						"misc": {
							"_unitLength": "m"
						},
						"name": "Wall",
						"outer_properties": {
							"material": {
								"aoUrl": null,
								"color": "#7c8eae",
								"displacementUrl": null,
								"emissionUrl": null,
								"flipY": false,
								"mapUrl": null,
								"metalnessUrl": null,
								"normalUrl": null,
								"repeat": [
									1.0,
									1.0
								],
								"rotation": 0.0,
								"roughnessUrl": null,
								"textureId": null
							}
						},
						"properties": {
							"height": {
								"length": 304.8
							},
							"textureA": "Brick",
							"textureB": "Brick",
							"thickness": {
								"length": 22.86
							}
						},
						"prototype": "lines",
						"selected": false,
						"type": "wall",
						"vertices": [
							"v-1773049006252-1",
							"v-1773049001517-0"
						],
						"visible": true
					}
				},
				"name": "First Floor",
				"opacity": 1.0,
				"order": 1.0,
				"selected": {
					"areas": [],
					"externalAreas": [],
					"holes": [],
					"items": [],
					"lines": [],
					"structures": [],
					"vertices": []
				},
				"structures": {

				},
				"vertices": {
					"v-1773049001517-0": {
						"areas": [
							"a-1773049007953-zohbv6kd"
						],
						"id": "v-1773049001517-0",
						"lines": [
							"l-1773049001516-88vkuras",
							"l-1773049007948-zjwivojd"
						],
						"misc": {

						},
						"name": "Vertex",
						"properties": {

						},
						"prototype": "vertices",
						"selected": false,
						"type": "vertex",
						"visible": true,
						"x": 906.733654229676,
						"y": -1814.59653481987
					},
					"v-1773049001517-1": {
						"areas": [
							"a-1773049007953-zohbv6kd"
						],
						"id": "v-1773049001517-1",
						"lines": [
							"l-1773049001516-88vkuras",
							"l-1773049004182-c3o2nppp"
						],
						"misc": {

						},
						"name": "Vertex",
						"properties": {

						},
						"prototype": "vertices",
						"selected": false,
						"type": "vertex",
						"visible": true,
						"x": 906.733654229676,
						"y": -1205.07272529606
					},
					"v-1773049004182-1": {
						"areas": [
							"a-1773049007953-zohbv6kd"
						],
						"id": "v-1773049004182-1",
						"lines": [
							"l-1773049004182-c3o2nppp",
							"l-1773049006252-pd9mcn52"
						],
						"misc": {

						},
						"name": "Vertex",
						"properties": {

						},
						"prototype": "vertices",
						"selected": false,
						"type": "vertex",
						"visible": true,
						"x": 1659.16222565825,
						"y": -1205.07272529606
					},
					"v-1773049006252-1": {
						"areas": [
							"a-1773049007953-zohbv6kd"
						],
						"id": "v-1773049006252-1",
						"lines": [
							"l-1773049006252-pd9mcn52",
							"l-1773049007948-zjwivojd"
						],
						"misc": {

						},
						"name": "Vertex",
						"properties": {

						},
						"prototype": "vertices",
						"selected": false,
						"type": "vertex",
						"visible": true,
						"x": 1659.16222565825,
						"y": -1814.59653481987
					}
				},
				"visible": true
			}
		},
		"meta": {
			"export_timestamp": "2026-02-27T05:56:32.991Z",
			"format_version": "2.1",
			"generated_by": "Site_Area_Generator",
			"session_id": 1772171792991.0
		},
		"pendingSnapshot": null,
		"redoStack": [],
		"selectedLayer": "layer-2",
		"showAllFloors": false,
		"suspendUndo": false,
		"undoStack": [],
		"unit": "m",
		"width": 1363.10769865368
	},
	"night_render": false,
	"render_quality": "4K",
	"target_coordinate_system": "right_handed_z_up",
	"threejs_camera": {
		"far": 450.0,
		"fov": 60.0,
		"near": 0.1,
		"position": {
			"x": 12.9950953750417,
			"y": 1.5,
			"z": -14.6503472017566
		},
		"rotation": {
			"x": -0.261420625236095,
			"y": 0.292134003869267,
			"z": 0.0768995765524746
		},
		"target": {
			"x": 10.115130689224,
			"y": -0.975028893535892,
			"z": -23.9012950118248
		}
	},
	"timestamp": 1773049181373.0
}